{"simulation_class": "GroundStateSearch", "sequential": {"recursive_keys": ["algorithm_params.trunc_params.chi_max"]}, "output_filename": "results_simulation.h5", "save_psi": true, "model_class": "MassiveSchwingerModelQubitEncoding", "model_params": {"model_name": "MassiveSchwingerModelVR", "Nf": 1, "Nr": 4, "m": [0.3335], "g": 1.0, "a": 0.3, "theta": 3.141592653589793, "m_corr": true, "L": 16, "bc_MPS": "finite", "bc_x": "open", "order": "default", "gauge_order": "after_source", "charge_mod": null, "compress_mpo": false, "version": "v2"}, "initial_state_params": {"method": "lat_product_state", "product_state": [["empty", "-4", "2", "1", "1"], ["full", "-4", "2", "1", "1"]], "allow_incommensurate": true, "version": "v1"}, "algorithm_class": "TwoSiteDMRGEngine", "algorithm_params": {"max_N_sites_per_ring": 18, "trunc_params": {"chi_max": [16, 32, 64, 128], "chi_min": null, "degeneracy_tol": 1e-10, "svd_min": 1e-14, "trunc_cut": 1e-10, "version": "v1"}, "version": "v1", "chi_list": null, "chi_list_reactivates_mixer": false, "combine": false, "lanczos_params": {"cutoff": 2.220446049250313e-14, "E_tol": 100, "E_shift": null, "min_gap": 1e-12, "N_max": 20, "N_min": 2, "P_tol": 1e-14, "reortho": false, "version": "v1", "N_cache": 20}, "mixer": true, "mixer_params": {"amplitude": 0.5, "decay": 5.0, "disable_after": null, "version": "v1"}, "start_env": 1, "max_hours": 8760, "max_sweeps": 50, "max_trunc_err": 0.0001, "min_sweeps": 1, "diag_method": "default", "E_tol_max": 0.0001, "E_tol_min": 5e-16, "E_tol_to_trunc": null, "max_E_err": 1e-09, "max_N_for_ED": 400, "max_S_err": 1e-08, "N_sweeps_check": 1, "norm_tol": 1e-05, "norm_tol_iter": 5, "norm_tol_final": 1e-10, "P_tol_max": 0.0001, "P_tol_to_trunc": 0.05, "P_tol_min": 1e-30, "update_env": 5}, "version": "v1"}